Workbook

Sheet 題庫
A1: 題號 | B1: 單元 | C1: 章節 | D1: 課程名稱（原始） | E1: 題型 | F1: 題目 | G1: 選項A | H1: 選項B | I1: 選項C | J1: 選項D | K1: 選項E | L1: 正確答案 | M1: 難度 | N1: 標籤 | O1: 解析 | P1: 法規依據 | Q1: 題目來源 | R1: 適用版本 | S1: 狀態 | T1: 圖片
A2: 1 | C2: 政府採購全生命週期概論 | D2: 政府採購全生命週期概論 | E2: 單選題 | F2: 依公共建設工程經費估算編列手冊總則篇，以下何者非屬工程建造費之編列架構？ | G2: 直接工程成本 | H2: 間接工程成本 | I2: 用地取得及拆遷補償費用 | J2: 工程預備費 | L2: C | M2: 難 | N2: 政府採購 | Q2: 公共工程雲端服務網 | R2: 115年1月起適用 | S2: 已發布
A3: 2 | C3: 政府採購全生命週期概論 | D3: 政府採購全生命週期概論 | E3: 單選題 | F3: 下列因應物價波動之方式，何者非屬妥適？ | G3: 計畫階段預為編列物調費及預備費 | H3: 個案契約依工程會工程採購契約範本採用3層級物調規定 | I3: 工程招標時請廠商提出放棄物調聲明書 | J3: 招標文件公告前再次訪查市場行情 | L3: C | M3: 難 | N3: 政府採購、物價調整 | Q3: 公共工程雲端服務網 | R3: 115年1月起適用 | S3: 已發布
A4: 3 | C4: 政府採購全生命週期概論 | D4: 政府採購全生命週期概論 | E4: 單選題 | F4: 下列何者非政府協調改善本國營造業缺工之措施？ | G4: 合理檢討移工規定 | H4: 加強本國勞工訓練媒合 | I4: 推動營建自動化 | J4: 全面開放移工進駐工地 | L4: D | M4: 難 | N4: 政府採購、營建人力 | Q4: 公共工程雲端服務網 | R4: 115年1月起適用 | S4: 已發布
A5: 4 | C5: 政府採購全生命週期概論 | D5: 政府採購全生命週期概論 | E5: 單選題 | F5: 依政府公共工程計畫與經費審議作業要點基本設計階段之必要圖說之規定，機關當次送審基本設計之工程建造經費達新臺幣多少時，應辦理替選方案評估，並將替選方案評估報告納為必要圖說文件？ | G5: 10億元 | H5: 4億元 | I5: 1億元 | J5: 5千萬元 | L5: A | M5: 難 | N5: 政府採購 | Q5: 公共工程雲端服務網 | R5: 115年1月起適用 | S5: 已發布
A6: 5 | C6: 政府採購全生命週期概論 | D6: 政府採購全生命週期概論 | E6: 單選題 | F6: 依共同性費用編列基準，專案研析後得計列之項目，不包含下列何者？ | G6: 基地一般性整理 | H6: 綠建築 | I6: 挑高空間 | J6: 智慧建築 | L6: A | M6: 難 | N6: 政府採購 | Q6: 公共工程雲端服務網 | R6: 115年1月起適用 | S6: 已發布
A7: 6 | C7: 政府採購全生命週期概論 | D7: 政府採購全生命週期概論 | E7: 單選題 | F7: 下列何者非屬「契約書圖條件不合理」之情形？ | G7: 保固年限過長 | H7: 訂定技術規格時，以功能或效益等精確方式說明招標需求，而不提供參考品牌 | I7: 材料綁標 | J7: 設計內容過簡要求廠商負設計責任 | L7: B | M7: 難 | N7: 政府採購、契約管理 | Q7: 公共工程雲端服務網 | R7: 115年1月起適用 | S7: 已發布
A8: 7 | C8: 政府採購全生命週期概論 | D8: 政府採購全生命週期概論 | E8: 單選題 | F8: 機關應務實評選規劃設計廠商，評定實務可行之方案，評選委員及工作小組應於評選前瞭解之事項包含？1.計畫需求與預算。2.期程。3.各廠商投標內容。4.契約變更方案。 | G8: 1234 | H8: 123 | I8: 124 | J8: 234 | L8: B | M8: 難 | N8: 政府採購、契約管理 | Q8: 公共工程雲端服務網 | R8: 115年1月起適用 | S8: 已發布
A9: 8 | C9: 政府採購全生命週期概論 | D9: 政府採購全生命週期概論 | E9: 單選題 | F9: 機關辦理採購應核實編列計畫預算，下列何者非考量之因素？ | G9: 機關需求 | H9: 使用年限 | I9: 未來契約可能因廠商違約重行招標之經費 | J9: 維護管理 | L9: C | M9: 難 | N9: 政府採購 | Q9: 公共工程雲端服務網 | R9: 115年1月起適用 | S9: 已發布
A10: 9 | C10: 政府採購全生命週期概論 | D10: 政府採購全生命週期概論 | E10: 單選題 | F10: 廠商如有違規棄土者，應要求限期清除；如未改善時，按契約規定 | G10: 扣款 | H10: 停止估驗 | I10: 終止契約或移請直轄市、縣(市)政府依規定查處 | J10: 以上皆是 | L10: D | M10: 中 | N10: 政府採購、契約管理 | Q10: 公共工程雲端服務網 | R10: 115年1月起適用 | S10: 已發布
A11: 10 | C11: 政府採購全生命週期概論 | D11: 政府採購全生命週期概論 | E11: 單選題 | F11: 機關辦理工程採購估驗計價，除契約另有約定，一般每期估驗款須扣除多少百分比之保留款？ | G11: 3％ | H11: 5% | I11: 6% | J11: 7% | L11: B | M11: 中 | N11: 政府採購、契約管理 | Q11: 公共工程雲端服務網 | R11: 115年1月起適用 | S11: 已發布
A12: 11 | C12: 政府採購全生命週期概論 | D12: 政府採購全生命週期概論 | E12: 單選題 | F12: 基於促進循環經濟效益，及輔導產業健全發展，工程會依行政院指示，推動部分工程材料可適材、適所、適量運用於公共工程，該等材料不包含下列何者？ | G12: 焚化再生粒料 | H12: 煉鋼爐碴 | I12: AC刨除料 | J12: 廢輪胎 | L12: D | M12: 難 | N12: 政府採購 | Q12: 公共工程雲端服務網 | R12: 115年1月起適用 | S12: 已發布
A13: 12 | C13: 政府採購全生命週期概論 | D13: 政府採購全生命週期概論 | E13: 單選題 | F13: 工程會透過專案檢討會議發現流標皆有其個案因素，下列何者為非？ | G13: 物價上漲 | H13: 預算不符實際 | I13: 工期不符實際 | J13: 設計書圖合約不合理 | L13: A | M13: 中 | N13: 政府採購 | Q13: 公共工程雲端服務網 | R13: 115年1月起適用 | S13: 已發布
A14: 13 | B14: 單元一 | C14: 第一章 公共工程施工品質管理制度理念與導入 | D14: 單元一：第一章 公共工程施工品質管理制度理念與導入 | E14: 單選題 | F14: 下列何者非監造單位及其派駐現場人員工作重點？ | G14: 對各施工作業應依工程契約及監造計畫實施抽查，並填具施工品質抽查紀錄表 | H14: 依規定填報監工日報表 | I14: 發現缺失時，應即通知廠商限期改善並採取矯正措施 | J14: 每日赴現場會同品管人員辦理自主檢查 | L14: D | M14: 難 | N14: 品管制度、監造 | Q14: 公共工程雲端服務網 | R14: 115年1月起適用 | S14: 已發布
A15: 14 | B15: 單元一 | C15: 第一章 公共工程施工品質管理制度理念與導入 | D15: 單元一：第一章 公共工程施工品質管理制度理念與導入 | E15: 單選題 | F15: 下列哪一項非機關或監造單位建立品質查證系統之內容？ | G15: 成立監造組織 | H15: 訂定監造計畫 | I15: 撰寫施工計畫 | J15: 辦理施工及材料設備之抽(查)驗作業 | L15: C | M15: 中 | N15: 品管制度、監造 | Q15: 公共工程雲端服務網 | R15: 115年1月起適用 | S15: 已發布
A16: 15 | B16: 單元一 | C16: 第一章 公共工程施工品質管理制度理念與導入 | D16: 單元一：第一章 公共工程施工品質管理制度理念與導入 | E16: 單選題 | F16: 品質管理的運作主要是利用下列哪些項目循環模式的管理加以落實？ | G16: 計劃、實施、查核及改善 | H16: 規劃、改善、結案及建檔 | I16: 需求、查核、執行及計畫 | J16: 稽核、變更、實施及確認 | L16: A | M16: 中 | N16: 品管制度 | Q16: 公共工程雲端服務網 | R16: 115年1月起適用 | S16: 已發布
A17: 16 | B17: 單元一 | C17: 第一章 公共工程施工品質管理制度理念與導入 | D17: 單元一：第一章 公共工程施工品質管理制度理念與導入 | E17: 單選題 | F17: 品管大師戴明博士(Dr.Deming)指出：「品質的問題的產生有百分之八十導因於 | G17: 管理不善 | H17: 設計不良 | I17: 業主需求不明 | J17: 無證照制度」 | L17: A | M17: 中 | N17: 品管制度 | Q17: 公共工程雲端服務網 | R17: 115年1月起適用 | S17: 已發布
A18: 17 | B18: 單元一 | C18: 第一章 公共工程施工品質管理制度理念與導入 | D18: 單元一：第一章 公共工程施工品質管理制度理念與導入 | E18: 單選題 | F18: 機關辦理公告金額以上工程，應辦理下列何者事項？ | G18: 委託監造招標文件內應訂明監造單位提報監造計畫 | H18: 工程招標文件內應訂明廠商提報品質計畫 | I18: 工程及委託監造招標文件內應訂明鋼筋、混凝土、瀝青混凝土及其他適當檢驗或抽驗項目，由符合CNS 17025規定之實驗室辦理，並出具報告 | J18: 以上皆是 | L18: D | M18: 難 | N18: 品管制度 | Q18: 公共工程雲端服務網 | R18: 115年1月起適用 | S18: 已發布
A19: 18 | B19: 單元一 | C19: 第一章 公共工程施工品質管理制度理念與導入 | D19: 單元一：第一章 公共工程施工品質管理制度理念與導入 | E19: 單選題 | F19: 查核金額以上工程，廠商應於何時將品管人員資料提報監造單位審查？ | G19: 竣工前 | H19: 竣工後 | I19: 開工前 | J19: 開工後 | L19: C | M19: 易 | N19: 品管制度、監造、工程查核 | Q19: 公共工程雲端服務網 | R19: 115年1月起適用 | S19: 已發布
A20: 19 | B20: 單元一 | C20: 第一章 公共工程施工品質管理制度理念與導入 | D20: 單元一：第一章 公共工程施工品質管理制度理念與導入 | E20: 單選題 | F20: 監造單位及其派駐現場人員工作重點，不包括下列何者？ | G20: 工地之人員、機具及材料等管理 | H20: 審查廠商所提施工計畫及品質計畫 | I20: 抽驗比對廠商所提之材料設備之出廠證明、檢驗文件、試驗報告等之內容、規格及有效日期 | J20: 對各施工作業實施抽查 | L20: A | M20: 中 | N20: 品管制度、監造 | Q20: 公共工程雲端服務網 | R20: 115年1月起適用 | S20: 已發布
A21: 20 | B21: 單元一 | C21: 第一章 公共工程施工品質管理制度理念與導入 | D21: 單元一：第一章 公共工程施工品質管理制度理念與導入 | E21: 單選題 | F21: 廠商專任工程人員工作重點，不包括下列何者？ | G21: 督察品管人員及現場施工人員，落實品質計畫 | H21: 品質文件、紀錄之管理 | I21: 督導按圖施工、解決施工技術問題 | J21: 查核(驗)工程時到場說明 | L21: B | M21: 中 | N21: 品管制度 | Q21: 公共工程雲端服務網 | R21: 115年1月起適用 | S21: 已發布
A22: 21 | B22: 單元一 | C22: 第一章 公共工程施工品質管理制度理念與導入 | D22: 單元一：第一章 公共工程施工品質管理制度理念與導入 | E22: 單選題 | F22: 廠商品管人員工作重點，不包括下列何者？ | G22: 訂定品質計畫 | H22: 執行內部品質稽核 | I22: 矯正預防措施之提出及追蹤改善 | J22: 填報施工日誌 | L22: D | M22: 易 | N22: 品管制度 | Q22: 公共工程雲端服務網 | R22: 115年1月起適用 | S22: 已發布
A23: 22 | B23: 單元一 | C23: 第一章 公共工程施工品質管理制度理念與導入 | D23: 單元一：第一章 公共工程施工品質管理制度理念與導入 | E23: 單選題 | F23: 以下何者正確？ | G23: 好的工程品質查證，主要係依賴查核達成 | H23: 品管表報文件是配合查核所自然產生的副產品，而不是另花時間刻意去編造 | I23: 承攬之工程獲得公共工程金質獎，施工廠商得免負品質無瑕疵的完全責任 | J23: 以上皆非 | L23: D | M23: 中 | N23: 品管制度 | Q23: 公共工程雲端服務網 | R23: 115年1月起適用 | S23: 已發布
A24: 23 | B24: 單元一 | C24: 第一章 公共工程施工品質管理制度理念與導入 | D24: 單元一：第一章 公共工程施工品質管理制度理念與導入 | E24: 單選題 | F24: 依｢工程施工查核小組組織準則｣規定，若某縣鄉公所辦理由某部會經費補助之工程，請問下列何機關之工程施工查核小組可以辦理該工程之查核？(1.行政院公共工程委員會2.補助之部會3.上級主管機關縣政府4.該鄉公所5.審計部) | G24: 1,2 | H24: 1,2,3 | I24: 2,3,4 | J24: 1,2,3,5 | L24: B | M24: 難 | N24: 品管制度、工程查核 | Q24: 公共工程雲端服務網 | R24: 115年1月起適用 | S24: 已發布
A25: 24 | B25: 單元一 | C25: 第一章 公共工程施工品質管理制度理念與導入 | D25: 單元一：第一章 公共工程施工品質管理制度理念與導入 | E25: 單選題 | F25: 依「公共工程施工品質管理作業要點」規定，若某公共工程之招標採購預算為2億5千萬元，決標金額為1億5千萬元，其施工廠商應設置至少幾位品管人員？ | G25: 1人 | H25: 2人 | I25: 3人 | J25: 不需設置 | L25: B | M25: 難 | N25: 品管制度、政府採購 | Q25: 公共工程雲端服務網 | R25: 115年1月起適用 | S25: 已發布
... A2539: 2538 | B2539: 單元二 | C2539: 第六章 建築工程之界面整合 | D2539: 單元二：第六章 建築工程之界面整合 | E2539: 單選題 | F2539: 管線埋設於樓板牆壁，管線應錯開，管與管中心間距應大於 | G2539: 2D | H2539: 3D | I2539: 4D | J2539: 5D | L2539: B | M2539: 易 | N2539: 界面整合 | Q2539: 公共工程雲端服務網 | R2539: 115年1月起適用 | S2539: 已發布

Sheet 欄位與匯入說明
A1: 欄位與匯入說明
A3: 本表為「可匯入系統的結構化題庫範本」。深藍欄位為既有資料；黃色欄位為未來需人工補齊的欄位。
A5: 欄位 | B5: 說明 | C5: 允許值 / 範例 | D5: 必填 | E5: 狀態
A6: 題號 | B6: 原始題庫序號，保留供追溯 | C6: 1 ~ 2538 | D6: 是 | E6: 既有
A7: 單元 | B7: 由課程名稱「：」前段解析 | C7: 單元一 / 單元二 / (概論類為空白) | D7: 是 | E7: 既有
A8: 章節 | B8: 由課程名稱「：」後段解析，為分類主鍵 | C8: 第一章 監造計畫與品質計畫指導 | D8: 是 | E8: 既有
A9: 課程名稱（原始） | B9: 原始未拆解之完整分類字串，供對照 | C9: 單元二：第二章 統計分析方法與應用 | D9: 是 | E9: 既有
A10: 題型 | B10: 目前全部為單選題 | C10: 單選題 / 複選題 / 是非題 | D10: 是 | E10: 既有
A11: 題目 | B11: 題幹（已移除內嵌選項） | C11: 純題幹文字 | D11: 是 | E11: 既有
A12: 選項A~D | B12: 四個選項，已由題目文字拆出 | C12: 純選項文字 | D12: 是 | E12: 既有
A13: 選項E | B13: 保留欄位，供未來5選項題使用 | C13: （目前皆空白） | D13: 否 | E13: 既有
A14: 正確答案 | B14: 正確選項代號 | C14: A / B / C / D | D14: 是 | E14: 既有
A15: 難度 | B15: 題目難度，供智慧複習與模擬考配比 | C15: 易 / 中 / 難 | D15: 否 | E15: 待填
A16: 標籤 | B16: 主題標籤，可多個以頓號分隔 | C16: 契約管理、物價指數 | D16: 否 | E16: 待填
... A22: 圖片 | B22: 題目附圖檔名或連結 | C22: （目前皆空白） | D22: 否 | E22: 待填
A25: 範例（已補齊待填欄位的樣貌）
A26: 題號 | B26: 4
A27: 單元 | B27: 單元一
A28: 章節 | B28: 第一章 公共工程施工品質管理制度理念與導入
A29: 題型 | B29: 單選題
A30: 題目 | B30: 依政府公共工程計畫與經費審議作業要點…應辦理替選方案評估之門檻為？
A31: 選項A | B31: 10億元
A32: 選項B | B32: 4億元
A33: 選項C | B33: 1億元
A34: 選項D | B34: 5千萬元
A35: 正確答案 | B35: A
A36: 難度 | B36: 中
A37: 標籤 | B37: 經費審議、替選方案
... A40: 狀態 | B40: 已發布
A43: 資料注意事項
A44: 1. 「單元二」出現兩組章節序：第一組為品管通用章節（監造計畫、統計分析、品質分析、進料檢驗、施工管制、品質稽核），第二組為機電專業章節（電氣、弱電、給排水、消防空調、電梯、界面整合）。因此請以「章節（完整名稱）」或「課程名稱（原始）」作為分類主鍵，勿僅用「單元＋章節序號」，否則會相互覆蓋。
A45: 2. 少數題目選項中含「dB (A)」為分貝A權單位，非選項代號；拆解時已依 A→B→C→D 順序處理，該記號正確保留於選項內文。
A46: 3. 選項E、難度、標籤、解析、法規依據、圖片目前為空白，為刻意保留之擴充欄位，待人工或AI補齊後再經審核發布。
A47: 4. 全部題目均為單選題，正確答案分布：A=579、B=572、C=630、D=757。

Sheet 章節統計
A1: 章節統計（公式連動題庫分頁）
A3: 單元 | B3: 章節（課程名稱原始） | C3: 題數
B4: 政府採購全生命週期概論 | C4: =COUNTIF(題庫!$D$2:$D$2539,"政府採購全生命週期概論") -> 12
A5: 單元一 | B5: 單元一：第一章 公共工程施工品質管理制度理念與導入 | C5: =COUNTIF(題庫!$D$2:$D$2539,"單元一：第一章 公共工程施工品質管理制度理念與導入") -> 28
A6: 單元一 | B6: 單元一：第二章 公共工程管理相關法規概要 | C6: =COUNTIF(題庫!$D$2:$D$2539,"單元一：第二章 公共工程管理相關法規概要") -> 136
A7: 單元一 | B7: 單元一：第三章 公共工程履約管理 | C7: =COUNTIF(題庫!$D$2:$D$2539,"單元一：第三章 公共工程履約管理") -> 134
A8: 單元一 | B8: 單元一：第四章 永續公共工程 | C8: =COUNTIF(題庫!$D$2:$D$2539,"單元一：第四章 永續公共工程") -> 50
A9: 單元一 | B9: 單元一：第五章 工程倫理 | C9: =COUNTIF(題庫!$D$2:$D$2539,"單元一：第五章 工程倫理") -> 36
A10: 單元二 | B10: 單元二：第一章 監造計畫與品質計畫指導 | C10: =COUNTIF(題庫!$D$2:$D$2539,"單元二：第一章 監造計畫與品質計畫指導") -> 195
A11: 單元二 | B11: 單元二：第二章 統計分析方法與應用 | C11: =COUNTIF(題庫!$D$2:$D$2539,"單元二：第二章 統計分析方法與應用") -> 180
A12: 單元二 | B12: 單元二：第三章 品質分析方法與應用 | C12: =COUNTIF(題庫!$D$2:$D$2539,"單元二：第三章 品質分析方法與應用") -> 204
A13: 單元二 | B13: 單元二：第四章 工程進料檢驗與管制 | C13: =COUNTIF(題庫!$D$2:$D$2539,"單元二：第四章 工程進料檢驗與管制") -> 230
A14: 單元二 | B14: 單元二：第五章 施工管制與檢驗 | C14: =COUNTIF(題庫!$D$2:$D$2539,"單元二：第五章 施工管制與檢驗") -> 216
A15: 單元二 | B15: 單元二：第六章 工程品質稽核 | C15: =COUNTIF(題庫!$D$2:$D$2539,"單元二：第六章 工程品質稽核") -> 175
A16: 單元二 | B16: 單元二：第一章 電氣設備工程品質管理實務 | C16: =COUNTIF(題庫!$D$2:$D$2539,"單元二：第一章 電氣設備工程品質管理實務") -> 142
A17: 單元二 | B17: 單元二：第二章 弱電(含中央監控)設備工程品質管理實務 | C17: =COUNTIF(題庫!$D$2:$D$2539,"單元二：第二章 弱電(含中央監控)設備工程品質管理實務") -> 232
A18: 單元二 | B18: 單元二：第三章 給排水衛生設備工程品質管理實務 | C18: =COUNTIF(題庫!$D$2:$D$2539,"單元二：第三章 給排水衛生設備工程品質管理實務") -> 158
A19: 單元二 | B19: 單元二：第四章 消防設備及空調設備工程品質管理實務 | C19: =COUNTIF(題庫!$D$2:$D$2539,"單元二：第四章 消防設備及空調設備工程品質管理實務") -> 151
A20: 單元二 | B20: 單元二：第五章 電梯設備工程品質管理實務 | C20: =COUNTIF(題庫!$D$2:$D$2539,"單元二：第五章 電梯設備工程品質管理實務") -> 161
A21: 單元二 | B21: 單元二：第六章 建築工程之界面整合 | C21: =COUNTIF(題庫!$D$2:$D$2539,"單元二：第六章 建築工程之界面整合") -> 98
B22: 總計 | C22: =SUM(C4:C21) -> 2538
A25: 答案分布
A26: 答案 | B26: 題數
A27: A | B27: =COUNTIF(題庫!$L$2:$L$2539,"A") -> 579
A28: B | B28: =COUNTIF(題庫!$L$2:$L$2539,"B") -> 572
A29: C | B29: =COUNTIF(題庫!$L$2:$L$2539,"C") -> 630
A30: D | B30: =COUNTIF(題庫!$L$2:$L$2539,"D") -> 757
